README.md
setup.cfg
setup.py
deeplabel/__init__.py
deeplabel/basemodel.py
deeplabel/client.py
deeplabel/exceptions.py
deeplabel/projects.py
deeplabel/auth/__init__.py
deeplabel/auth/tokens.py
deeplabel/auth/users.py
deeplabel/contrib/__init__.py
deeplabel/contrib/utils.py
deeplabel/contrib/downloaders/__init__.py
deeplabel/contrib/downloaders/frame_downloader.py
deeplabel/contrib/exporters/__init__.py
deeplabel/contrib/exporters/coco.py
deeplabel/contrib/exporters/pascal_voc.py
deeplabel/contrib/importers/__init__.py
deeplabel/contrib/importers/pascalvoc.py
deeplabel/contrib/importers/utils.py
deeplabel/contrib/infer/__init__.py
deeplabel/contrib/infer/images.py
deeplabel/contrib/infer/videos.py
deeplabel/feedback/__init__.py
deeplabel/feedback/gallery.py
deeplabel/feedback/videos.py
deeplabel/infer/__init__.py
deeplabel/infer/folders.py
deeplabel/infer/notebooks.py
deeplabel/infer/presign.py
deeplabel/infer/types.py
deeplabel/infer/gallery/__init__.py
deeplabel/infer/gallery/detections.py
deeplabel/infer/gallery/gallery_graphs.py
deeplabel/infer/gallery/gallery_tasks.py
deeplabel/infer/gallery/images.py
deeplabel/infer/graphs/__init__.py
deeplabel/infer/graphs/graph_edges.py
deeplabel/infer/graphs/graph_nodes.py
deeplabel/infer/videos/__init__.py
deeplabel/infer/videos/detections.py
deeplabel/infer/videos/video_chapters.py
deeplabel/infer/videos/video_graphs.py
deeplabel/infer/videos/video_keyphrases.py
deeplabel/infer/videos/video_keywords.py
deeplabel/infer/videos/video_links.py
deeplabel/infer/videos/video_quiz.py
deeplabel/infer/videos/video_sentences.py
deeplabel/infer/videos/video_summary.py
deeplabel/infer/videos/video_tasks.py
deeplabel/label/__init__.py
deeplabel/label/dl_models.py
deeplabel/label/folders.py
deeplabel/label/label_maps.py
deeplabel/label/labels.py
deeplabel/label/gallery/__init__.py
deeplabel/label/gallery/detections.py
deeplabel/label/gallery/gallery_tasks.py
deeplabel/label/gallery/images.py
deeplabel/label/videos/__init__.py
deeplabel_sdk.egg-info/PKG-INFO
deeplabel_sdk.egg-info/SOURCES.txt
deeplabel_sdk.egg-info/dependency_links.txt
deeplabel_sdk.egg-info/requires.txt
deeplabel_sdk.egg-info/top_level.txt
