Metadata-Version: 2.1
Name: deeplabel-sdk
Version: 1.2.0
Summary: python sdk to get data from deeplabel
Home-page: https://github.com/streamingo/deeplabel
Author: Streamingo Solutions
Author-email: deeplabel-team@streamingo.ai
Project-URL: Bug Reports, https://github.com/streamingo/deeplabel/issues
Project-URL: Source, https://github.com/streamingo/deeplabel/
Classifier: Development Status :: 3 - Alpha
Classifier: Intended Audience :: Developers
Classifier: Topic :: Software Development :: Build Tools
Classifier: License :: OSI Approved :: MIT License
Classifier: Programming Language :: Python :: 3
Classifier: Programming Language :: Python :: 3.6
Classifier: Programming Language :: Python :: 3.7
Classifier: Programming Language :: Python :: 3.8
Classifier: Programming Language :: Python :: 3.9
Classifier: Programming Language :: Python :: 3.10
Classifier: Programming Language :: Python :: 3 :: Only
Requires-Python: >=3.8, <4
Requires-Dist: requests
Requires-Dist: addict
Requires-Dist: pydantic==1.10.7
Requires-Dist: case-converter
Requires-Dist: shapely
Requires-Dist: python3-wget
Requires-Dist: pascal-voc-writer
Requires-Dist: opencv-python
Requires-Dist: coloredlogs
Requires-Dist: tqdm
Requires-Dist: dataclasses
Requires-Dist: yarl
Requires-Dist: Pillow
Requires-Dist: pycryptodome
